isensor/__init__.py
isensor/bit_depth.py
isensor/grid.py
isensor/pixel.py
isensor/sensor.py
isensor/sensor_positions.py
isensor/sensor_type.py
isensor/sensors_db.py
isensor-0.2.0.dist-info/licenses/LICENSE
isensor-0.2.0.dist-info/METADATA
isensor-0.2.0.dist-info/WHEEL
isensor-0.2.0.dist-info/top_level.txt
isensor-0.2.0.dist-info/RECORD
