Metadata-Version: 2.4
Name: isensor
Version: 0.2.0
Summary: Image sensor model and database
Author-email: Anton Sharapov <sharapov.anton@gmail.com>
License-Expression: MIT
Project-URL: Homepage, https://github.com/SharapovAnton/ISensor
Project-URL: Source, https://github.com/SharapovAnton/ISensor
Project-URL: Issues, https://github.com/SharapovAnton/ISensor/issues
Classifier: Programming Language :: Python :: 3
Classifier: Programming Language :: Python :: 3 :: Only
Classifier: Operating System :: OS Independent
Classifier: Topic :: Software Development :: Libraries
Classifier: Typing :: Typed
Requires-Python: >=3.8
License-File: LICENSE
Requires-Dist: numpy>=1.23
Requires-Dist: allytools>=0.6.0
Provides-Extra: dev
Requires-Dist: pytest; extra == "dev"
Requires-Dist: mypy; extra == "dev"
Requires-Dist: ruff; extra == "dev"
Provides-Extra: qa
Requires-Dist: tox; extra == "qa"
Requires-Dist: pre-commit; extra == "qa"
Dynamic: license-file
